nim_mmcif-0.0.21.dist-info/RECORD
nim_mmcif-0.0.21.dist-info/WHEEL
nim_mmcif-0.0.21.dist-info/top_level.txt
nim_mmcif-0.0.21.dist-info/METADATA
nim_mmcif/_version.py
nim_mmcif/__init__.py
nim_mmcif/nim_mmcif.so
nim_mmcif/_dummy.cpython-312-darwin.so
nim_mmcif/_dummy.c
nim_mmcif/nim_mmcif.nim
nim_mmcif/mmcif.nim
nim_mmcif/dataclasses.py
