Metadata-Version: 2.1
Name: nim-mmcif
Version: 0.0.21
Summary: mmCIF parser written in Nim with Python bindings
Author: claude opus
Author-email: lucidrains <lucidrains@gmail.com>
License: MIT
Project-URL: Homepage, https://github.com/lucidrains/nim-mmcif
Project-URL: Bug Tracker, https://github.com/lucidrains/nim-mmcif/issues
Project-URL: Source Code, https://github.com/lucidrains/nim-mmcif
Keywords: mmcif,cif,protein,structure,bioinformatics,structural-biology,parser,crystallography,nim,pdb
Classifier: Development Status :: 3 - Alpha
Classifier: Intended Audience :: Science/Research
Classifier: Intended Audience :: Developers
Classifier: License :: OSI Approved :: MIT License
Classifier: Operating System :: OS Independent
Classifier: Programming Language :: Python :: 3
Classifier: Programming Language :: Python :: 3.8
Classifier: Programming Language :: Python :: 3.9
Classifier: Programming Language :: Python :: 3.10
Classifier: Programming Language :: Python :: 3.11
Classifier: Programming Language :: Python :: 3.12
Classifier: Programming Language :: Other
Classifier: Topic :: Scientific/Engineering :: Bio-Informatics
Classifier: Topic :: Scientific/Engineering :: Chemistry
Classifier: Topic :: Software Development :: Libraries :: Python Modules
Requires-Python: >=3.8
Requires-Dist: setuptools>=61.0
Requires-Dist: nimporter>=1.1.0
Provides-Extra: dev
Requires-Dist: pytest>=7.0; extra == "dev"
Provides-Extra: test
Requires-Dist: pytest>=7.0; extra == "test"
